Metadata-Version: 2.1
Name: simple-arthmetic-calc
Version: 0.1.0
Summary: Arithmetic Operations on Decimal and Binary numbers.
Home-page: UNKNOWN
Author: Manoahar Naidu
Author-email: beesettim27@gmail.com
License: MIT
Keywords: calculator,simple calculator,arithmetic operations
Platform: UNKNOWN
Classifier: Development Status :: 5 - Production/Stable
Classifier: Intended Audience :: Education
Classifier: Operating System :: Microsoft :: Windows :: Windows 10
Classifier: License :: OSI Approved :: MIT License
Classifier: Programming Language :: Python :: 3
License-File: LICENCE.txt
